execution_time/__init__.py
execution_time/execution_time.py
execution_time/tests/__init__.py
execution_time/tests/test_execution.py
Execution_Time-1.1.0.dist-info/LICENSE
Execution_Time-1.1.0.dist-info/METADATA
Execution_Time-1.1.0.dist-info/WHEEL
Execution_Time-1.1.0.dist-info/top_level.txt
Execution_Time-1.1.0.dist-info/RECORD
