Metadata-Version: 2.1
Name: Execution-Time
Version: 1.1.0
Summary: package which provides you with a decorator to measure execution time of functions
Home-page: https://github.com/siddhant-curious/Python-Method-Execution-Time
Author: Siddhant Chhabra <siddhant1042@gmail.com>
Author-email: siddhant1042@gmail.com
License: MIT
Platform: UNKNOWN
Classifier: License :: OSI Approved :: MIT License
Classifier: Programming Language :: Python :: 3
Classifier: Programming Language :: Python :: 3.7
Classifier: Operating System :: OS Independent
